{
  "bundler": "rollup",
  "shimport": "2.0.4",
  "assets": {
    "main": "client.d73b15ef.js"
  },
  "css": {
    "main": [
      "client-7ec35abd.css"
    ]
  },
  "dependencies": {
    "index.svelte": [
      "index.2d5e793e.js",
      "inject_styles.5607aec6.js",
      "index-05a5af07.css"
    ],
    "create-account.svelte": [
      "create-account.f71fef0f.js",
      "inject_styles.5607aec6.js",
      "create-account-bfc049a0.css"
    ],
    "change-email.svelte": [
      "change-email.72012f35.js",
      "inject_styles.5607aec6.js",
      "change-email-7780a81f.css"
    ],
    "contact.svelte": [
      "contact.56a31682.js",
      "inject_styles.5607aec6.js"
    ],
    "offline.svelte": [
      "offline.afae17a0.js",
      "inject_styles.5607aec6.js"
    ],
    "privacy.svelte": [
      "privacy.af6de248.js",
      "inject_styles.5607aec6.js"
    ],
    "status.svelte": [
      "status.16a277ef.js",
      "inject_styles.5607aec6.js"
    ],
    "about.svelte": [
      "about.c4942b68.js",
      "inject_styles.5607aec6.js"
    ],
    "terms.svelte": [
      "terms.4aea99ba.js",
      "inject_styles.5607aec6.js"
    ],
    "tests/[id].svelte": [
      "[id].89d16128.js",
      "inject_styles.5607aec6.js"
    ],
    "help.svelte": [
      "help.c3f6a324.js",
      "inject_styles.5607aec6.js"
    ],
    "link/[id].svelte": [
      "[id].1581f5ef.js",
      "inject_styles.5607aec6.js"
    ],
    "play/index.svelte": [
      "index.fdcf1f6e.js",
      "AdblockAlert.444b5434.js",
      "GuideCard.bd396dfb.js",
      "Loading.05c87030.js",
      "inject_styles.5607aec6.js",
      "AdblockAlert-cddd02f2.css",
      "GuideCard-909fbf0f.css",
      "Loading-6d3e7c1c.css",
      "index-9084697f.css"
    ],
    "play/ffa/index.svelte": [
      "index.6da53ed6.js",
      "Loading.05c87030.js",
      "inject_styles.5607aec6.js",
      "Loading-6d3e7c1c.css"
    ],
    "play/ffa/[id].svelte": [
      "[id].233fa56f.js",
      "AdblockAlert.444b5434.js",
      "GuideCard.bd396dfb.js",
      "Loading.05c87030.js",
      "inject_styles.5607aec6.js",
      "AdblockAlert-cddd02f2.css",
      "GuideCard-909fbf0f.css",
      "Loading-6d3e7c1c.css",
      "[id]-0b6ded83.css"
    ],
    "shop.svelte": [
      "shop.64a7072e.js",
      "AdblockAlert.444b5434.js",
      "inject_styles.5607aec6.js",
      "AdblockAlert-cddd02f2.css",
      "shop-948a85e0.css"
    ],
    "test.svelte": [
      "test.d91636b3.js",
      "inject_styles.5607aec6.js"
    ]
  },
  "legacy_assets": {
    "main": "client.702330b2.js"
  }
}