{
  "bundler": "rollup",
  "shimport": "2.0.4",
  "assets": {
    "main": "client.a0bd9dc2.js"
  },
  "css": {
    "main": [
      "client-208562c5.css"
    ]
  },
  "dependencies": {
    "index.svelte": [
      "index.88ca0dbb.js",
      "Checkbox.fdc90f15.js",
      "inject_styles.5607aec6.js",
      "index-a47d9b0e.css"
    ],
    "create-account.svelte": [
      "create-account.46b2f013.js",
      "inject_styles.5607aec6.js",
      "create-account-b7607b99.css"
    ],
    "referral-link.svelte": [
      "referral-link.85b2aadf.js",
      "Loading.1326df1b.js",
      "inject_styles.5607aec6.js",
      "Loading-6d3e7c1c.css",
      "referral-link-91f5e3e1.css"
    ],
    "feltrom/admin.svelte": [
      "admin.7239facc.js",
      "Loading.1326df1b.js",
      "RefreshButton.fddbfbdd.js",
      "inject_styles.5607aec6.js",
      "Loading-6d3e7c1c.css",
      "RefreshButton-3df42125.css",
      "admin-28b3b360.css"
    ],
    "privacy.svelte": [
      "privacy.91016cf4.js",
      "Infos.4f3c6e4d.js",
      "inject_styles.5607aec6.js",
      "privacy-e22f729e.css"
    ],
    "status.svelte": [
      "status.fb315f61.js",
      "inject_styles.5607aec6.js"
    ],
    "legal.svelte": [
      "legal.c9ff9d8f.js",
      "inject_styles.5607aec6.js",
      "legal-32170f98.css"
    ],
    "login.svelte": [
      "login.2b3de4c3.js",
      "inject_styles.5607aec6.js",
      "login-b7607b99.css"
    ],
    "terms.svelte": [
      "terms.30998f7c.js",
      "inject_styles.5607aec6.js",
      "terms-35c65d7c.css"
    ],
    "link/[id].svelte": [
      "[id].4d235e0b.js",
      "Loading.1326df1b.js",
      "inject_styles.5607aec6.js",
      "Loading-6d3e7c1c.css"
    ],
    "play/index.svelte": [
      "index.203c55da.js",
      "Infos.4f3c6e4d.js",
      "Checkbox.fdc90f15.js",
      "Loading.1326df1b.js",
      "RefreshButton.fddbfbdd.js",
      "AdblockAlert.5df306b6.js",
      "inject_styles.5607aec6.js",
      "Loading-6d3e7c1c.css",
      "RefreshButton-3df42125.css",
      "AdblockAlert-2d5bd460.css",
      "index-a9822222.css"
    ],
    "play/ffa/index.svelte": [
      "index.d44d5d9f.js",
      "Loading.1326df1b.js",
      "inject_styles.5607aec6.js",
      "Loading-6d3e7c1c.css"
    ],
    "play/ffa/[id].svelte": [
      "[id].24e3fd46.js",
      "Infos.4f3c6e4d.js",
      "Checkbox.fdc90f15.js",
      "Loading.1326df1b.js",
      "RefreshButton.fddbfbdd.js",
      "AdblockAlert.5df306b6.js",
      "inject_styles.5607aec6.js",
      "Loading-6d3e7c1c.css",
      "RefreshButton-3df42125.css",
      "AdblockAlert-2d5bd460.css",
      "[id]-2bfd4b7e.css"
    ],
    "shop.svelte": [
      "shop.ca68d42d.js",
      "inject_styles.5607aec6.js",
      "shop-05698334.css"
    ]
  }
}