{
  "bundler": "rollup",
  "shimport": "2.0.4",
  "assets": {
    "main": "client.4628337f.js"
  },
  "css": {
    "main": [
      "client-43b5da58.css"
    ]
  },
  "dependencies": {
    "index.svelte": [
      "index.6d448690.js",
      "inject_styles.5607aec6.js",
      "index-05a5af07.css"
    ],
    "referral-link.svelte": [
      "referral-link.7d069925.js",
      "Loading.60330cf5.js",
      "inject_styles.5607aec6.js",
      "Loading-6d3e7c1c.css",
      "referral-link-ebaab53e.css"
    ],
    "contact.svelte": [
      "contact.cb0637b9.js",
      "inject_styles.5607aec6.js"
    ],
    "feltrom/admin.svelte": [
      "admin.9cad85df.js",
      "Loading.60330cf5.js",
      "RefreshButton.99e10a16.js",
      "inject_styles.5607aec6.js",
      "Loading-6d3e7c1c.css",
      "RefreshButton-cddd02f2.css",
      "admin-3d6ee500.css"
    ],
    "offline.svelte": [
      "offline.7fcab421.js",
      "inject_styles.5607aec6.js"
    ],
    "privacy.svelte": [
      "privacy.fe2bb427.js",
      "Infos.5f0f892c.js",
      "inject_styles.5607aec6.js",
      "privacy-ae4b8860.css"
    ],
    "status.svelte": [
      "status.65b33b89.js",
      "inject_styles.5607aec6.js"
    ],
    "about.svelte": [
      "about.b40fa5ff.js",
      "inject_styles.5607aec6.js"
    ],
    "legal.svelte": [
      "legal.9e647dd2.js",
      "inject_styles.5607aec6.js",
      "legal-95a0a22d.css"
    ],
    "terms.svelte": [
      "terms.1f5cd29f.js",
      "inject_styles.5607aec6.js",
      "terms-b34a3226.css"
    ],
    "tests/[id].svelte": [
      "[id].4062b333.js",
      "inject_styles.5607aec6.js"
    ],
    "help.svelte": [
      "help.a04dea55.js",
      "inject_styles.5607aec6.js"
    ],
    "link/[id].svelte": [
      "[id].cdb0ddae.js",
      "Loading.60330cf5.js",
      "inject_styles.5607aec6.js",
      "Loading-6d3e7c1c.css"
    ],
    "play/index.svelte": [
      "index.316d0639.js",
      "Loading.60330cf5.js",
      "RefreshButton.99e10a16.js",
      "AdblockAlert.b7a33e1f.js",
      "inject_styles.5607aec6.js",
      "Loading-6d3e7c1c.css",
      "RefreshButton-cddd02f2.css",
      "AdblockAlert-e75c9c22.css",
      "index-202fb85f.css"
    ],
    "play/ffa/index.svelte": [
      "index.f3b6a10e.js",
      "Loading.60330cf5.js",
      "inject_styles.5607aec6.js",
      "Loading-6d3e7c1c.css"
    ],
    "play/ffa/[id].svelte": [
      "[id].49a82e6a.js",
      "Loading.60330cf5.js",
      "RefreshButton.99e10a16.js",
      "Infos.5f0f892c.js",
      "AdblockAlert.b7a33e1f.js",
      "inject_styles.5607aec6.js",
      "Loading-6d3e7c1c.css",
      "RefreshButton-cddd02f2.css",
      "AdblockAlert-e75c9c22.css",
      "[id]-03ea2bac.css"
    ],
    "shop.svelte": [
      "shop.9050a65e.js",
      "inject_styles.5607aec6.js",
      "shop-0074d698.css"
    ],
    "test.svelte": [
      "test.098de91a.js",
      "inject_styles.5607aec6.js"
    ]
  },
  "legacy_assets": {
    "main": "client.50b5b3b1.js"
  }
}