{
  "bundler": "rollup",
  "shimport": "2.0.4",
  "assets": {
    "main": "client.1a295bac.js"
  },
  "css": {
    "main": [
      "client-b2b0a392.css"
    ]
  },
  "dependencies": {
    "index.svelte": [
      "index.57b9ae6a.js",
      "inject_styles.5607aec6.js",
      "index-05a5af07.css"
    ],
    "referral-link.svelte": [
      "referral-link.52aeb4b3.js",
      "Loading.7a5283a3.js",
      "inject_styles.5607aec6.js",
      "Loading-6d3e7c1c.css",
      "referral-link-24585f0a.css"
    ],
    "contact.svelte": [
      "contact.e4808111.js",
      "inject_styles.5607aec6.js"
    ],
    "feltrom/admin.svelte": [
      "admin.61ae2d73.js",
      "Loading.7a5283a3.js",
      "RefreshButton.dc947b0f.js",
      "inject_styles.5607aec6.js",
      "Loading-6d3e7c1c.css",
      "RefreshButton-cddd02f2.css",
      "admin-3d6ee500.css"
    ],
    "offline.svelte": [
      "offline.79b845d4.js",
      "inject_styles.5607aec6.js"
    ],
    "privacy.svelte": [
      "privacy.bd2ab9f8.js",
      "Infos.91f0dd52.js",
      "inject_styles.5607aec6.js",
      "privacy-ae4b8860.css"
    ],
    "status.svelte": [
      "status.3248d384.js",
      "inject_styles.5607aec6.js"
    ],
    "about.svelte": [
      "about.77dd5ef9.js",
      "inject_styles.5607aec6.js"
    ],
    "legal.svelte": [
      "legal.bf85319c.js",
      "inject_styles.5607aec6.js",
      "legal-95a0a22d.css"
    ],
    "terms.svelte": [
      "terms.b4c2bb17.js",
      "inject_styles.5607aec6.js",
      "terms-b34a3226.css"
    ],
    "tests/[id].svelte": [
      "[id].e0ae3baa.js",
      "inject_styles.5607aec6.js"
    ],
    "help.svelte": [
      "help.88a2ea6c.js",
      "inject_styles.5607aec6.js"
    ],
    "link/[id].svelte": [
      "[id].eb34ac51.js",
      "Loading.7a5283a3.js",
      "inject_styles.5607aec6.js",
      "Loading-6d3e7c1c.css"
    ],
    "play/index.svelte": [
      "index.87b7fd0f.js",
      "Loading.7a5283a3.js",
      "RefreshButton.dc947b0f.js",
      "AdblockAlert.5cba4ecf.js",
      "inject_styles.5607aec6.js",
      "Loading-6d3e7c1c.css",
      "RefreshButton-cddd02f2.css",
      "AdblockAlert-e75c9c22.css",
      "index-202fb85f.css"
    ],
    "play/ffa/index.svelte": [
      "index.38528be7.js",
      "Loading.7a5283a3.js",
      "inject_styles.5607aec6.js",
      "Loading-6d3e7c1c.css"
    ],
    "play/ffa/[id].svelte": [
      "[id].0d992581.js",
      "Loading.7a5283a3.js",
      "RefreshButton.dc947b0f.js",
      "Infos.91f0dd52.js",
      "AdblockAlert.5cba4ecf.js",
      "inject_styles.5607aec6.js",
      "Loading-6d3e7c1c.css",
      "RefreshButton-cddd02f2.css",
      "AdblockAlert-e75c9c22.css",
      "[id]-3703d8ff.css"
    ],
    "shop.svelte": [
      "shop.d5b2e0de.js",
      "inject_styles.5607aec6.js",
      "shop-0074d698.css"
    ],
    "test.svelte": [
      "test.0c79afd3.js",
      "inject_styles.5607aec6.js"
    ]
  }
}